{
  "build_host": "a84448598@7.212.231.184",
  "control_example": {
    "action": "kill",
    "command_id": "unique-kill-001",
    "target_run_id": "current"
  },
  "control_path": "run_stream_control.json",
  "elapsed_seconds": 8.6,
  "exec_control_example": {
    "action": "exec",
    "command_id": "unique-exec-001",
    "command_xz_b64": "<base64(xz(command text))>",
    "target": "build",
    "timeout_seconds": 0
  },
  "exit_code": 0,
  "host": "lhrphis01120",
  "live_manifest": "run_stream_live/cmd_20260614_104414_inspect_ark_bench_wrapper_1781433834/live.json",
  "note": "command_id=inspect_ark_bench_wrapper_1781433834 command_sha256=b5dca426fb8a3dd31af89d8f3f22947d70ba403ab3ffd6795e9cdd1b7a62dd84",
  "phase": "done",
  "phone_dir": "/home/ayoub/runphone_dir",
  "phone_host": "a84448598@10.123.51.179",
  "pid": 1026529,
  "run_id": "cmd_20260614_104414_inspect_ark_bench_wrapper_1781433834",
  "state": "finished-control-command",
  "updated_utc": "2026-06-14 10:44:23 UTC"
}
