{
  "build_host": "a84448598@7.212.231.184",
  "control_example": {
    "action": "kill",
    "command_id": "unique-kill-001",
    "target_run_id": "current"
  },
  "control_path": "run_stream_control.json",
  "elapsed_seconds": 0.0,
  "exec_control_example": {
    "action": "exec",
    "command_id": "unique-exec-001",
    "command_xz_b64": "<base64(xz(command text))>",
    "target": "build",
    "timeout_seconds": 0
  },
  "host": "lhrphis01120",
  "live_manifest": "run_stream_live/cmd_20260615_113157_module-separate-merge-probe-20260615113127/live.json",
  "note": "command_id=module-separate-merge-probe-20260615113127 command_sha256=49f16dc23a7cbbfd4bb3eee656b29fc56dd8293733e3b1f41b98f4480655e824",
  "phase": "control-phone_host",
  "phone_dir": "/home/ayoub/runphone_dir",
  "phone_host": "a84448598@10.123.51.179",
  "pid": 2391193,
  "run_id": "cmd_20260615_113157_module-separate-merge-probe-20260615113127",
  "state": "running-control-command",
  "updated_utc": "2026-06-15 11:31:57 UTC"
}
